nonebot_plugin_smart_reply/__init__.py
nonebot_plugin_smart_reply/config.py
nonebot_plugin_smart_reply/getopenai.py
nonebot_plugin_smart_reply/keywordhandle.py
nonebot_plugin_smart_reply/txtToImg.py
nonebot_plugin_smart_reply/utils.py
nonebot_plugin_smart_reply/resource/audio/cnm傻逼吃屎滚.aac
nonebot_plugin_smart_reply/resource/audio/你寄吧谁啊(振声!).aac
nonebot_plugin_smart_reply/resource/audio/你寄吧谁啊我超.aac
nonebot_plugin_smart_reply/resource/audio/你是不是有毛病.aac
nonebot_plugin_smart_reply/resource/audio/你正常一点.aac
nonebot_plugin_smart_reply/resource/audio/傻逼.aac
nonebot_plugin_smart_reply/resource/audio/南通啊.aac
nonebot_plugin_smart_reply/resource/audio/去死吧.aac
nonebot_plugin_smart_reply/resource/audio/变态啊.aac
nonebot_plugin_smart_reply/resource/audio/啊你好烦啊.aac
nonebot_plugin_smart_reply/resource/audio/我草泥马.aac
nonebot_plugin_smart_reply/resource/audio/操你妈.aac
nonebot_plugin_smart_reply/resource/audio/救命啊.aac
nonebot_plugin_smart_reply/resource/audio/草泥马(慢).aac
nonebot_plugin_smart_reply/resource/audio/非礼啊.aac
nonebot_plugin_smart_reply/resource/json/data.json
nonebot_plugin_smart_reply-0.15.114514.dist-info/METADATA
nonebot_plugin_smart_reply-0.15.114514.dist-info/WHEEL
nonebot_plugin_smart_reply-0.15.114514.dist-info/top_level.txt
nonebot_plugin_smart_reply-0.15.114514.dist-info/RECORD
