Metadata-Version: 2.1
Name: nonebot-plugin-smart-reply
Version: 0.15.114514
Summary: nonebot2的融合了openai, newbing, 词库的智障回复插件
Home-page: https://github.com/Special-Week/nonebot_plugin_smart_reply
Author: Special-Week
Author-email: HuaMing27499@gmail.com
Requires-Python: >=3.9.0
Requires-Dist: EdgeGPT
Requires-Dist: revChatGPT
Requires-Dist: pillow
Requires-Dist: nonebot2
Requires-Dist: nonebot-adapter-onebot
Requires-Dist: httpx
